panel4all/VERSION
panel4all/__init__.py
panel4all/pollresults.py
panel4all-1.0.0.dist-info/LICENSE
panel4all-1.0.0.dist-info/METADATA
panel4all-1.0.0.dist-info/WHEEL
panel4all-1.0.0.dist-info/top_level.txt
panel4all-1.0.0.dist-info/RECORD
